{
  "alt_ids": [
    {
      "name": "spartan",
      "value": 874
    }
  ],
  "collections": [
    "Sean Cody"
  ],
  "description": "<p>After graduating from high school, some people decide to backpack through  Europe or just take some time off.</p>\n<p>Ronnie decided he was going to do something different.</p>\n<p>He'd been kind of a trouble maker in school. He'd pulled down his pants to show his cock to a girl in front of a big group, he'd picked on some other kids, and he'd broken into the gym's weight room after hours (for various reasons).</p>\n<p>When we met Ronnie he was 18 but had <strong>just</strong> graduated from high school.  </p>\n<p>He told us that he wanted to do one more wild thing before settling down and heading off to college...</p>",
  "models": [
    {
      "name": "Ronnie",
      "person_id": 19863
    }
  ],
  "release_date": "2009-09-14",
  "scene_id": 2697751,
  "series": [],
  "tags": [
    "Solo",
    "Athlete/Jock"
  ],
  "title": "Ronnie"
}