{
  "alt_ids": [
    {
      "name": "spartan",
      "value": 2963
    }
  ],
  "collections": [
    "Men"
  ],
  "description": "The Brotherhood Of The Traveling Underwear 1",
  "models": [
    {
      "name": "Johnny Rapid",
      "person_id": 20324
    },
    {
      "name": "Mike De Marko",
      "person_id": 39424
    }
  ],
  "release_date": "2013-07-17",
  "scene_id": 3688551,
  "series": [
    "Big Dicks At School"
  ],
  "tags": [
    "One-on-One",
    "Blowjob",
    "Face Fuck",
    "Teen",
    "Twink",
    "Muscular",
    "Anal",
    "25-34",
    "Piercing",
    "American",
    "Brown Hair",
    "Short Hair",
    "Average Dick",
    "Average Body"
  ],
  "title": "The Brotherhood Of The Traveling Underwear 1"
}