{
  "alt_ids": [
    {
      "name": "spartan",
      "value": 43321
    }
  ],
  "collections": [
    "Men"
  ],
  "description": "Adam Thicke is strapped for cash and finds an open dancer position at the local gay bar. His roommate Wesley Woods assists him with learning the moves and the ways of the scene\u2014and primes that cock for all the ass it\u2019ll get once he lands the job.",
  "models": [
    {
      "name": "Adam Thicke",
      "person_id": 40333
    },
    {
      "name": "Wesley Woods",
      "person_id": 39934
    }
  ],
  "release_date": "2017-08-14",
  "scene_id": 3709871,
  "series": [
    "Str8 to Gay"
  ],
  "tags": [],
  "title": "The Straight Stripper"
}