{
  "alt_ids": [
    {
      "name": "spartan",
      "value": 15811
    }
  ],
  "collections": [
    "Men"
  ],
  "description": "Gabriel Cross has had enough of pleasing everyone else at the university. It\u2019s time for him to do something that he wants to do. Luckily for McKensie Cross that \u201csomething\u201c is him! Gabriel fucks a hot load out of McKensie before spunking all over his smooth stomach.",
  "models": [
    {
      "name": "Gabriel Cross",
      "person_id": 39543
    },
    {
      "name": "McKensie Cross",
      "person_id": 39561
    }
  ],
  "release_date": "2015-04-28",
  "scene_id": 3710371,
  "series": [
    "Men of UK"
  ],
  "tags": [
    "European",
    "Brown Hair",
    "Short Hair",
    "Average Dick"
  ],
  "title": "Ivy League Part 3"
}