{
  "collections": [
    "Lucas Entertainment"
  ],
  "description": "Julian Vincenzo and Steve Hunt show off their talents in this action packed scene from Auditions 23. Steves gaping hole gets stretched with Julians huge cock and the scene ends with a hot cum shot in Steves mouth.",
  "models": [
    {
      "name": "Julian Vincenzo",
      "person_id": null
    },
    {
      "name": "Steve Hunt",
      "person_id": null
    }
  ],
  "release_date": "2009-11-21",
  "scene_id": 278,
  "series": "Auditions 23",
  "title": "Steve Hunt and Julian Vincenzo"
}