{
  "collections": [
    "Austin Wilde"
  ],
  "description": "Austin Wilde is a pretty straight up guy. He knows what he wants, and when he wants it, he has no problem saying so. Adam Wirthmore is a student who passes his free time online in several chat rooms. And it seems as though Austin has taken an interest. So when he calls Adam one afternoon, he's got only one thing on his mind. Luckily for Austin, Adam is down with the program and free for the afternoon. A short bike ride later and the both of them will get what they really want.Enjoy!",
  "models": [
    {
      "name": "Austin Wilde",
      "person_id": 7497
    },
    {
      "name": "Adam Wirthmore",
      "person_id": 9827
    }
  ],
  "release_date": "2011-07-19",
  "scene_id": 30956,
  "series": "A068 - Austin Wilde & Adam Wirthmore",
  "tags": [
    "Amateur",
    "Anal Sex",
    "Athletic",
    "Brunette",
    "Climax",
    "Colored hair",
    "Condom",
    "Cum swallow",
    "Dark Hair",
    "Facial Hair",
    "HD Movies",
    "Hardcore",
    "Masturbation",
    "Oral",
    "Tattoo/Piercing"
  ],
  "title": "Da Booty Call"
}