{
  "collections": [
    "Raging Stallion"
  ],
  "description": "Petter Fill is cooling off in the shower house when Pedro Andreaswalks in to join him. Peter is built like a football player big andmuscular with light hair covering his pecs and abs. Pedro is big andburly with a tight stomach and a nice fat uncut cock hanging betweenhis legs. After a few glances these men are all over each other. Pedrogoes down on Peter first filling his mouth with dick as he works thehead and the entire fat shaft of Peter's uncut cock. Pedro sucks itdown his throat as Peter groans with pleasure.When Pedro sits with his massive erection bouncing off his abs Peterquickly finds his position and goes in for some deep throat dick action.Peter's ass is next up for some attention and Pedro follows throughwith his tongue diving deep into the pulsing hole. After a tongue bathPeter's hole is ready for a big dick and Pedro supplies it, pushingdeep into him and working his butt with a beautiful rhythm. Peterenjoys every thrust as his asshole is stretched repeatedly. But Peterwants a turn too and he puts Pedro on his side to have easy accessto his waiting hole. Pedro takes it like a pro as Peter presses into thedark crevice before beginning a nice pounding. Pedro is pushed overthe edge with one last stroke and releases a mound of cum beforePeter pulls out and shoots.",
  "models": [
    {
      "name": "Pedro Andreas",
      "person_id": 19973
    },
    {
      "name": "Petter Fill",
      "person_id": 19977
    }
  ],
  "release_date": "2010-01-21",
  "scene_id": 38344,
  "series": "Casa Del Sol",
  "tags": [
    "Anal",
    "Hairy",
    "Oral",
    "Outdoor Sex",
    "Tattoos",
    "butt play",
    "cum shots",
    "masturbation",
    "rimming"
  ],
  "title": "Casa Del Sol"
}