{
  "collections": [
    "Men Over 30"
  ],
  "description": "If you like your men buffed and hairy then this is definitely for you.  Dirk Willis is a very hot daddy with a muscular body that loves to show it off for your viewing pleasure. This solo scene will satisfy all lovers of hairy, manly guys and keep you wanting more. Dirk shows it all off for our cameras and will get your juices flowing in no time -- making you salivate by proudly jerking off and flaunting one of the best features of his beautiful ass by teasing his tight hole.",
  "models": [
    {
      "name": "Dirk Willis",
      "person_id": 28088
    }
  ],
  "release_date": "2013-02-07",
  "scene_id": 59774,
  "tags": [],
  "title": "The Daddy Next Door"
}