{
  "alt_ids": [
    {
      "name": "spartan",
      "value": 7438
    }
  ],
  "collections": [
    "Reality Dudes"
  ],
  "description": "",
  "models": [
    {
      "name": "Alexander",
      "person_id": 20664
    },
    {
      "name": "Benie",
      "person_id": 20662
    },
    {
      "name": "Garrett",
      "person_id": 20666
    },
    {
      "name": "Nicholas",
      "person_id": 20668
    }
  ],
  "release_date": "2010-10-13",
  "scene_id": 2835261,
  "series": [
    "Dick Dorm"
  ],
  "tags": [
    "Solo",
    "Masturbation",
    "Muscular",
    "Black Hair",
    "Blond Hair",
    "Gay",
    "Shaved"
  ],
  "title": "What People Do"
}