{
  "collections": [
    "Device Bondage"
  ],
  "description": "Live Show Mondays brings you part 4 of 4 from the October live show that featured Gia DiMarco, with Maestro co-fucking.\nBound in a custom metal piece, Gia is put in the ultimate \"fuck me\" position. We start by flogging her swollen pussy, and move on to foot caning. We trap her big nipples in homemade nipple clamps, gag her, then we start in on the real fun.\nMaestro uses her cunt for his amusement and gives her a hard fucking. We make Gia cum so many times she almost can't stand it. When we start fingering her and making her squirt her scream of ecstasy fills the room, how mush liquid can we finger bang out of her pussy before she passes out?",
  "directors": [],
  "models": [
    {
      "name": "Gia DiMarco",
      "person_id": 21436
    },
    {
      "name": "Maestro",
      "person_id": 11928
    }
  ],
  "release_date": "2010-11-29",
  "scene_id": 11286,
  "tags": [
    "bdsm",
    "big tits",
    "bondage",
    "caning",
    "Corporal Punishment",
    "domination",
    "Facial",
    "Fingering",
    "flogging",
    "foot torture",
    "gag",
    "Handler",
    "humiliation",
    "metal bondage",
    "MILF",
    "nipple clamps",
    "straight",
    "submission"
  ],
  "title": "Milf made to squirt over & over."
}