{
  "collections": [
    "Fucked and Bound"
  ],
  "description": "Lyla has been chained to a toilet and left until her holes are needed again. Owen enters and gets right to it, manhandling her and using her mouth for his pleasure. She is helpless against him and can only submit to his wishes, which is to see her fuck the toilet handle while she sucks his cock. Lyla is then tied to the wall with one leg pulled up to fully expose her pussy and prevent her from stopping his cock from entering her filthy cunt. She fights back, but in the end Owen gets what he wants. Next she is put in two different ground ties for him to have his way with her more.",
  "directors": [
    {
      "name": "The Pope",
      "person_id": 60
    }
  ],
  "models": [
    {
      "name": "Lyla Storm",
      "person_id": 33882
    },
    {
      "name": "Owen Gray",
      "person_id": 39181
    }
  ],
  "release_date": "2013-09-15",
  "scene_id": 30544,
  "tags": [
    "Anal",
    "Athletic",
    "BDSM",
    "Blowjob",
    "brunet",
    "Brunette",
    "Corporal Punishment",
    "Domination",
    "foreskin",
    "Humiliation",
    "Latin",
    "natural boobs",
    "Role Play",
    "Rope Bondage",
    "Rough Sex",
    "shaped",
    "shaved",
    "slim",
    "Straight",
    "Sub",
    "Submission",
    "switch",
    "Tattoo",
    "the wall",
    "Vaginal Penetration",
    "versatile",
    "white"
  ],
  "title": "Getting What She Deserves"
}