{
  "collections": [
    "TS Pussy Hunters"
  ],
  "description": "A building wide power outage makes fast fuck buddies out of Becca and Vivi who pass the time waiting for the lights to come back on with flirting and foreplay. Just as Becca puts Vivi's pussy in her mouth, the lights flicker back to life but neither girl is interested in stopping. Becca in fact, has something very special to show Vivi and now with the lights on Vivi will get a very good look at Becca's hot, hard cock. This discover drives Vivi wild and the two fuck like mad on the bed. Becca is so turned on from fucking Vivi's ass, pussy and mouth, that she nearly cums inside Vivi, pulling out at the last minute to cum on her belly.",
  "directors": [],
  "models": [
    {
      "name": "Becca Fatale",
      "person_id": 51925
    },
    {
      "name": "Vivi Marie",
      "person_id": 51948
    }
  ],
  "release_date": "2014-05-30",
  "scene_id": 35525,
  "tags": [
    "blowjob",
    "Cock Worship",
    "role play",
    "straight",
    "TS",
    "TS Fucks Female",
    "TS",
    "Vaginal Penetration"
  ],
  "title": "Hey Neighbour, Could you Spare a Cup of Shag? Power Outage Fucking"
}