{
  "collections": [
    "Electro Sluts"
  ],
  "description": "Watch the genuine fear in Ella Nova's eyes as she's pushed to her limits with electro predicament bondage, flogging, intense tickle torture, double electro penetration, the glowing violet wand and the cattle prod. Simone Sonay rewards her with an incredibly hot, multiple orgasmic anal strap-on fucking!",
  "models": [
    {
      "name": "Simone Sonay",
      "person_id": 34687
    },
    {
      "name": "Ella Nova ",
      "person_id": 51866
    }
  ],
  "release_date": "2015-04-09",
  "scene_id": 37797,
  "tags": [
    "anal",
    "predicament bondage",
    "bondage",
    "flogging",
    "cattle prod",
    "violet wand",
    "lesbian"
  ],
  "title": "Electric Mindfuck: Ella Nova's Intense Anal Electro Predicament!"
}