{
  "collections": [
    "Public Disgrace"
  ],
  "description": "Proxy Page begs to service everyone she passes on the street. This pathetic slut exposes her huge ass and perky tits to anyone who will give her the attention she craves. After being humiliated in public she is dragged into a bar where she takes cock after cock in her gaping asshole. She begs her dominant to fill her mouth and soak her from head to toe. Opening her ass up she takes double anal and still wants more. Finally, after this pathetic slave is completely used up she is brutally fisted and drenched in cum.",
  "directors": [],
  "models": [
    {
      "name": "Bella Beretta",
      "person_id": 58150
    },
    {
      "name": "Nikki Thorne",
      "person_id": 58279
    },
    {
      "name": "Proxy Paige",
      "person_id": 24708
    },
    {
      "name": "RAM",
      "person_id": 20259
    }
  ],
  "release_date": "2015-10-09",
  "scene_id": 38327,
  "tags": [
    "Anal",
    "BDSM",
    "Blowjob",
    "Boot",
    "Brunette",
    "Corporal Punishment",
    "Discipline",
    "Domination",
    "Double Anal",
    "fake boobs",
    "Female Slave",
    "foreskin",
    "Gaping",
    "Humiliation",
    "Latinx",
    "natural boobs",
    "other hair color",
    "Public",
    "Rope Bondage",
    "Rough Sex",
    "shaped",
    "Slave",
    "Straight",
    "Sub",
    "Submission",
    "switch",
    "Vaginal Penetration",
    "Voyeur",
    "white"
  ],
  "title": "Anal Whore Services all the Shoes"
}