{
  "collections": [
    "Struggling Babes"
  ],
  "description": "Daisy Lee is tied up by her female mistress Sarah Kay. She gets punished, teased, and pleased in a very erotic way. See how she enjoys her screaming orgasm!",
  "directors": [],
  "models": [
    {
      "name": "Daisy Lee",
      "person_id": 60458
    },
    {
      "name": "Sarah Kay",
      "person_id": 61137
    }
  ],
  "release_date": "2018-06-20",
  "scene_id": 43542,
  "tags": [
    "BDSM",
    "Blonde",
    "Bondage",
    "Crop",
    "Dildo",
    "Dominatrix",
    "dungeon",
    "Female Slave",
    "Femdom",
    "Flogging",
    "Gag",
    "High Heels",
    "Hitachi",
    "Lesbian",
    "LezDom",
    "Metal Bondage",
    "natural boobs",
    "Nipple Clamps",
    "Nylons Stockings",
    "Slapping",
    "slim",
    "Straight",
    "Tattoo",
    "Partner Studio",
    "Vaginal Penetration",
    "Vibrator",
    "white"
  ],
  "title": "Daisy Lee gets Vibed and Pussy Slapped"
}