{
  "collections": [
    "Femme Fatale Films"
  ],
  "description": "Mistress Carly has a new mummified sex slave and she intends to use him for her pleasure, but in order for her to get turned on he needs to endure some punishment first. Once she's finished using him, she milks him dry to keep him compliant and leaves him wrapped on the bed for the next time.",
  "directors": [],
  "models": [
    {
      "name": "Mistress Carly",
      "person_id": 61835
    },
    {
      "name": "Slave",
      "person_id": 61639
    }
  ],
  "release_date": "2019-09-04",
  "scene_id": 45133,
  "tags": [
    "CBT",
    "Clothespins",
    "Corset",
    "Dominatrix",
    "Facesitting",
    "foreskin",
    "Gimp",
    "Handjob",
    "High Heels",
    "Leather",
    "Male Sub",
    "Mask",
    "Nipple Clamps",
    "other hair color",
    "Slave",
    "Straight",
    "thirdparty",
    "Vaginal Penetration",
    "white"
  ],
  "title": "Fucked & Milked"
}