{
  "collections": [
    "Harmony Fetish"
  ],
  "description": "Blonde pin up babe Lissa Love goes to see her doctor to seek help with her problem\u2026she can\u2019t have an orgasm. The horny doctor closely examines Lissa, shoving all different kinds of dildos into her shaved pussy before he slams her wet eager slit with his huge throbbing man meat!",
  "directors": [],
  "models": [
    {
      "name": "Dirty Dog",
      "person_id": 61175
    },
    {
      "name": "Lissa Love",
      "person_id": 63023
    }
  ],
  "release_date": "2020-07-20",
  "scene_id": 46499,
  "tags": [
    "big dick",
    "Big Tits",
    "Blonde",
    "Curvy",
    "Deepthroat",
    "Doctor",
    "Facefucking",
    "Facial",
    "Fetish",
    "Fingering",
    "Fishnets",
    "foreskin",
    "Kinky",
    "other hair color",
    "Pussy Eating",
    "shaved",
    "Straight",
    "Partner Studio",
    "Vaginal Penetration",
    "Vibrator",
    "white"
  ],
  "title": "Curvy Blonde Gets Abused By Her Doctor"
}