{
  "collections": [
    "Wired Pussy"
  ],
  "description": "In this role play update Devi Emerson plays a bitchy inmate at the Sunnydale Detention Facility. She is always getting in fights and causing problems for her counselors, so she is taken to Dr. Rayne for some more extreme treatments. Unfortunately this shoot had to be cut short before we got to the electricity, but I think you will enjoy this bonus none the less!",
  "models": [
    {
      "name": "Amber Rayne",
      "person_id": 12631
    },
    {
      "name": "Devi Emerson",
      "person_id": 17680
    }
  ],
  "release_date": "2008-10-06",
  "scene_id": 5644,
  "tags": [
    "bdsm",
    "cattle prod",
    "Corporal Punishment",
    "Cut",
    "dominatrix",
    "electrical play",
    "electricity",
    "electro clamp",
    "electro dildo",
    "Face Sitting",
    "femdom",
    "Fingering",
    "humiliation",
    "lesbian",
    "lesbian anal",
    "LezDom",
    "Pussy Eating",
    "role play",
    "slave",
    "straight",
    "strap on",
    "TENS Unit",
    "Zapper"
  ],
  "title": "Sunnydale Detention Facility"
}