{
  "collections": [
    "Wired Pussy"
  ],
  "description": "Heaven Lee is really into bondage but this was her first shoot with pentration, and her first time with electroplay. She said that adding those things really made the scene more intense for her. Then I took her out for a stroll using the remote controlled stim.",
  "directors": [
    {
      "name": "Cowgirl",
      "person_id": 110
    }
  ],
  "models": [
    {
      "name": "Heaven Lee",
      "person_id": 340
    }
  ],
  "release_date": "2003-03-06",
  "scene_id": 813,
  "tags": [
    "Anal",
    "BDSM",
    "Bondage",
    "Cattle Prod",
    "Corporal Punishment",
    "Dominatrix",
    "Electric Dildo",
    "Electrical Play",
    "Electro Clamp",
    "Facesitting",
    "Femdom",
    "Fingering",
    "Humiliation",
    "Lesbian",
    "LezDom",
    "Pussy Eating",
    "Slave",
    "Straight",
    "Strap On",
    "Tens Unit",
    "Zapper"
  ],
  "title": "Heaven Lee"
}