{
  "collections": [
    "ChaosMen"
  ],
  "description": "This time out Ajax was determined to be a top, so I thought I would put him with a known element who always has a great time- Adam.\nOnce again, having Ajax's ass played with got him hard, and I swear the kid is a bottom but won't admit it. Adam does a stellar job of blowing him and teasing his ass.\nWe tried a few different positions, and we ended up fucking on a chair. It was a little challenging, but they both pulled it off.\nAjax was have trouble getting close to nutting. We tried and tried, and he just wasn't gonna get there. Frankly I think he needed a dick in his butt!\nFinally I put a big 'ole butt plug up his ass, and he laid there as Adam worked himself to nut all over his cock. He cums, but man, its just not noticeable. Adam, however, had ROPES of cum shooting out. Probably his best cumshot ever.\nEnjoy!",
  "models": [
    {
      "name": "Ajax",
      "person_id": 3243
    },
    {
      "name": "Adam",
      "person_id": 3179
    }
  ],
  "release_date": "2008-05-23",
  "scene_id": 714,
  "tags": [
    "Sex Act - Anal Sex Fucking",
    "Chest - Smooth/Natural",
    "Cock - Hung",
    "Build - Muscular",
    "Pubic Hair - Intact",
    "Ethnicity - White Guys",
    "Hair - Blond",
    "Sex Act - Kissing",
    "Sex Act - Oral",
    "Video - HD - High Def"
  ],
  "title": "Adam & Ajax - Wrapped"
}