{
  "collections": [
    "ChaosMen"
  ],
  "description": "Adair has been with guys before, apparently doing everything from topping to bottoming, but cock sucking is struggle for him.\nI don't think we have had a traditional full Service video in a while, so Sean does all the work in this video.\nAdair is a bit nervous to start with, and does rely on the porn playing for him. It takes Sean a couple minutes to get him hard, and then we get some great cock sucking! Sean knows what he is doing!\nWhen Sean flips Adair doggie-style, boy does Adair ever look ready to Bottom. He loved having his ass rimmed, while Sean dived in deep with his tongue. Adair says he prefers to top, but I would push to that great ass pillaged!\nAdair jerks-off pretty fast in order to cum, so I knew Sean likely couldn't pull a load out of him.\nBut we get an awesome facial, as Adair coats Sean's face and mouth with a giant load!",
  "models": [
    {
      "name": "Adair",
      "person_id": 8192
    },
    {
      "name": "Sean Peyton",
      "person_id": 8158
    }
  ],
  "release_date": "2016-12-20",
  "scene_id": 8197,
  "tags": [
    "Build - Lean",
    "Build - Swimmer",
    "Build - Twink",
    "Chest - Smooth/Trimmed",
    "Ethnicity - White Guys",
    "Hair - Brown/DK Blond",
    "Pubic Hair - Trimmed",
    "Sex Act - Ass Eating Rimming",
    "Sex Act - Facial  Cum Eating",
    "Sex Act - Oral",
    "Theme - Serviced",
    "Video - HD - High Def",
    "X-Tras - Piercings",
    "X-Tras - Tattoos"
  ],
  "title": "Adair & Sean Peyton - Serviced"
}