{
  "collections": [
    "BoyNapped"
  ],
  "description": "Brad Holt is found tied to a table by Kenzie Madison and Ashton Bradley. Kenzie and Ashton begin by teasing Brad's body, kissing and biting down his neck, over his chest to his nipples, and down to his cut dick. Aston then begins working on Brad Holt's feet, tickling them and torturing them, while Kenzie begins to play with Brad's cock and finally jerks him till he cums.",
  "models": [
    {
      "name": "Ashton Bradley",
      "person_id": 6523
    },
    {
      "name": "Brad Holt",
      "person_id": 6537
    },
    {
      "name": "Kenzie Madison",
      "person_id": 6651
    }
  ],
  "release_date": "2011-05-04",
  "scene_id": "179",
  "tags": [
    "Blowjob",
    "Bondage",
    "Fetish",
    "Domination",
    "Tickling",
    "Masturbation",
    "Twinks",
    "Deep Throat",
    "Black Hair",
    "Brown Hair",
    "Shaved",
    "Cut",
    "Short Hair",
    "Cum Being Jerked Off",
    "Licking & Biting",
    "Clothed",
    "Other Location",
    "British",
    "Cock and Ball Torture",
    "Milking",
    "Pinwheel",
    "Rope",
    "Edging"
  ],
  "title": "Ashton Bradley, Brad Holt & Kenzie Madison"
}